nqueens/__init__.py
nqueens/code.py
nqueens/test.py
nqueens-1.0.4.dist-info/LICENSE
nqueens-1.0.4.dist-info/METADATA
nqueens-1.0.4.dist-info/WHEEL
nqueens-1.0.4.dist-info/top_level.txt
nqueens-1.0.4.dist-info/RECORD
