Metadata-Version: 2.1
Name: nqueens
Version: 1.0.4
Summary: A package to get nqueens.
Home-page: https://github.com/toshihiroryuu/nqueens---PyPI-Package
Author: Athul Mathew Konoor
Author-email: athulmathewkonoor@gmail.com
License: UNKNOWN
Platform: UNKNOWN
Classifier: Programming Language :: Python :: 3
Classifier: License :: OSI Approved :: MIT License
Classifier: Operating System :: OS Independent
Requires-Python: >=3.6
Requires-Dist: gtts (>=2.2.0)
